py_vt-0.0.3.dist-info/DESCRIPTION.rst
py_vt-0.0.3.dist-info/METADATA
py_vt-0.0.3.dist-info/RECORD
py_vt-0.0.3.dist-info/WHEEL
py_vt-0.0.3.dist-info/metadata.json
py_vt-0.0.3.dist-info/top_level.txt
pyvt/__init__.py
