Metadata-Version: 2.0
Name: py-vt
Version: 0.0.3
Summary: A Python API for the Virginia Tech Timetable of Classes
Home-page: UNKNOWN
Author: UNKNOWN
Author-email: UNKNOWN
License: UNKNOWN
Keywords: Virgina Tech Timetable API
Platform: UNKNOWN
Classifier: License :: OSI Approved :: MIT License
Classifier: Programming Language :: Python :: 3.6
Requires-Dist: beautifulsoup4 (==4.5.1)
Requires-Dist: requests (==2.12.4)
